dataqa_extractor/.python-version
dataqa_extractor/__init__.py
dataqa_extractor/constants.py
dataqa_extractor/extract.py
dataqa_extractor/run.py
dataqa_extractor-0.1.3.dist-info/METADATA
dataqa_extractor-0.1.3.dist-info/WHEEL
dataqa_extractor-0.1.3.dist-info/entry_points.txt
dataqa_extractor-0.1.3.dist-info/RECORD
